{
  "resourceType": "StructureMap",
  "id": "intervention-order-to-procedurerequest",
  "text": {
    "status": "generated",
    "div": "<div xmlns=\"http://www.w3.org/1999/xhtml\"></div>" 
  },
  "url": "http://hl7.org/fhir/us/cqframework/cqfmeasures/StructureMap/intervention-order-to-procedurerequest",
  "name": "intervention-order-to-procedurerequest",
  "title": "QDM Intervention, Order to QICore Procedure Request",
  "status": "draft",
  "structure": [
    {
      "url": "http://hl7.org/fhir/StructureDefinition/QDM/intervention_order",  
      "mode": "source"
    },
    {
      "url": "http://hl7.org/fhir/us/qicore/StructureDefinition/qicore-procedurerequest", 
      "mode": "target"
    }
  ],
  "group": [
    {
      "name": "intervention-order-to-procedurerequest",
      "typeMode": "none",
      "input": [
        {
          "name": "source",
          "mode": "source"
        },
        {
          "name": "target",
          "mode": "target"
        }
      ],
      "rule": [
  {
          "name": "interventionOrder-to-intent",
          "source": [
            {
              "context": "source",
              "variable": "a"
            }
          ],
          "target": [
            {
              "context": "target",
              "contextType": "variable",
              "element": "intent",
              "transform": "evaluate",
              "parameter": [
                {
                  "valueString": "order"
                }
              ]
            }
          ]
        },   
        {
          "name": "negationRationale-to-extension.procedurerequest-reasonRefused",
          "source": [
            {
              "context": "source",
              "element": "negationRationale",
              "variable": "a"
            }
          ],
          "target": [
            {
              "context": "target",
              "contextType": "variable",
              "element": "extension.procedurerequest-reasonRefused",
              "transform": "copy"
            }
          ]
        },
        {
          "name": "reason-to-reasonCode",
          "source": [
            {
              "context": "source",
              "element": "reason",
              "variable": "a"
            }
          ],
          "target": [
            {
              "context": "target",
              "contextType": "variable",
              "element": "reasonCode",
              "transform": "copy"
            }
          ]
        },
        {
          "name": "authorDateTime-to-AuthoredOn",
          "source": [
            {
              "context": "source",
              "element": "authorDateTime",
              "variable": "a"
            }
          ],
          "target": [
            {
              "context": "target",
              "contextType": "variable",
              "element": "AuthoredOn",
              "transform": "copy"
            }
          ]
        },
        {
          "name": "code-to-code",
          "source": [
            {
              "context": "source",
              "element": "code",
              "variable": "a"
            }
          ],
          "target": [
            {
              "context": "target",
              "contextType": "variable",
              "element": "code",
              "transform": "copy"
            }
          ]
        },
		{
          "name": "id-to-id",
          "source": [
            {
              "context": "source",
              "element": "id",
              "variable": "a"
            }
          ],
          "target": [
            {
              "context": "target",
              "contextType": "variable",
              "element": "id",
              "transform": "copy"
            }
          ]
        },
		{
          "name": "source-to-requester",
          "source": [
            {
              "context": "source",
              "element": "source",
              "variable": "a"
            }
          ],
          "target": [
            {
              "context": "target",
              "contextType": "variable",
              "element": "requester",
              "transform": "copy"
            }
          ]
        }
     ]
    }
  ]
}
